setup.py
blogtools/__init__.py
blogtools/admin.py
blogtools/feeds.py
blogtools/managers.py
blogtools/models.py
blogtools/urls.py
blogtools/utils.py
blogtools/views.py
blogtools/templatetags/__init__.py
blogtools/templatetags/blogtools_tags.py
blogtools/tests/__init__.py
blogtools/tests/urls.py
blogtools/tests/blug/__init__.py
blogtools/tests/blug/admin.py
blogtools/tests/blug/feeds.py
blogtools/tests/blug/models.py
blogtools/tests/blug/urls.py
blogtools/tests/blug/views.py
blogtools/tests/blug/templatetags/__init__.py
blogtools/tests/blug/templatetags/blug_tags.py
glamkit_blogtools.egg-info/PKG-INFO
glamkit_blogtools.egg-info/SOURCES.txt
glamkit_blogtools.egg-info/dependency_links.txt
glamkit_blogtools.egg-info/not-zip-safe
glamkit_blogtools.egg-info/top_level.txt