Metadata-Version: 1.0
Name: glamkit-blogtools
Version: 0.5.0
Summary: Mini framework for making Django blog apps.
Home-page: http://github.com/glamkit/glamkit-blogtools
Author: Julien Phalip
Author-email: julien@interaction.net.au
License: UNKNOWN
Platform: UNKNOWN
Classifier: Development Status :: 4 - Beta
Classifier: Environment :: Web Environment
Classifier: Intended Audience :: Developers
Classifier: License :: OSI Approved :: BSD License
Classifier: Operating System :: OS Independent
Classifier: Programming Language :: Python
Classifier: Framework :: Django
